_metamart_testutils/__init__.py
_metamart_testutils/ometa.py
_metamart_testutils/data/dvdrental.zip
_metamart_testutils/helpers/__init__.py
_metamart_testutils/helpers/assumption.py
_metamart_testutils/helpers/docker.py
_metamart_testutils/helpers/markers.py
_metamart_testutils/kafka/__init__.py
_metamart_testutils/kafka/load_csv_data.py
_metamart_testutils/kafka/schema_registry_container.py
_metamart_testutils/postgres/__init__.py
_metamart_testutils/postgres/conftest.py
_metamart_testutils/pydantic/__init__.py
_metamart_testutils/pydantic/test_utils.py
_metamart_testutils/pytest_metamart/__init__.py
_metamart_testutils/pytest_metamart/plugin.py
_metamart_testutils/pytest_metamart/test_utils.py
airflow_provider_metamart/__init__.py
airflow_provider_metamart/hooks/__init__.py
airflow_provider_metamart/hooks/metamart.py
airflow_provider_metamart/lineage/__init__.py
airflow_provider_metamart/lineage/backend.py
airflow_provider_metamart/lineage/callback.py
airflow_provider_metamart/lineage/operator.py
airflow_provider_metamart/lineage/runner.py
airflow_provider_metamart/lineage/status.py
airflow_provider_metamart/lineage/config/__init__.py
airflow_provider_metamart/lineage/config/commons.py
airflow_provider_metamart/lineage/config/loader.py
metadata/__main__.py
metadata/__version__.py
metadata/cmd.py
metadata/py.typed
metadata/antlr/split_listener.py
metadata/automations/runner.py
metadata/cli/app.py
metadata/cli/dataquality.py
metadata/cli/ingest.py
metadata/cli/lineage.py
metadata/cli/profile.py
metadata/cli/restore.py
metadata/cli/usage.py
metadata/clients/aws_client.py
metadata/clients/azure_client.py
metadata/clients/domo_client.py
metadata/config/common.py
metadata/data_quality/api/models.py
metadata/data_quality/builders/i_validator_builder.py
metadata/data_quality/builders/pandas_validator_builder.py
metadata/data_quality/builders/sqa_validator_builder.py
metadata/data_quality/interface/test_suite_interface.py
metamart_ingestion-1.6.0.0.dev0.dist-info/LICENSE
metamart_ingestion-1.6.0.0.dev0.dist-info/METADATA
metamart_ingestion-1.6.0.0.dev0.dist-info/WHEEL
metamart_ingestion-1.6.0.0.dev0.dist-info/entry_points.txt
metamart_ingestion-1.6.0.0.dev0.dist-info/top_level.txt
metamart_ingestion-1.6.0.0.dev0.dist-info/RECORD
